{"evals_30": 12, "success_30": 12, "failures_30": 0, "f_success_30": 4, "f_failures_30": 0, "a_success_30": 2, "a_failures_30": 0, "i_success_30": 3, "i_failures_30": 0, "r_success_30": 3, "r_failures_30": 0, "total_monthly": [{"x": "2022-08", "y": 12}, {"x": "2022-09", "y": 45}, {"x": "2022-10", "y": 11}, {"x": "2023-01", "y": 11}, {"x": "2023-03", "y": 110}, {"x": "2023-04", "y": 155}, {"x": "2023-05", "y": 279}, {"x": "2023-06", "y": 30}, {"x": "2023-07", "y": 438}, {"x": "2023-12", "y": 80}, {"x": "2024-06", "y": 12}]}